Workbook
Name CL_TIPO_ACTIVO_LID: CAT_TIPO_ACTIVO_LID!$A$2:$A$15
Name CL_MONEDA: CAT_MONEDA!$A$2:$A$171

Sheet VALIDACION
A1: RESUMEN DE VALIDACIÓN
A2: Total celdas con error de formato: | C2: =SUM(CHK!A2:D201)
A3: Estado: | C3: =IF(C2=0,"✔ SIN ERRORES DE FORMATO","✖ REVISAR: "&C2&" celda(s) marcada(s) en rojo")
A5: Orden | B5: Campo | C5: Tipo | D5: Long | E5: Catálogo | F5: # Errores | G5: # Vacíos (obligatorio)
A6: 1 | B6: TIPO_ACTIVO | C6: NUMERICO | D6: 2,0 | E6: Tipo_Activo_LID | F6: =SUM(CHK!A2:A201) | G6: =COUNTBLANK('SECCION_1_LID'!A2:A201)
A7: 2 | B7: SALDO_ID | C7: NUMERICO | D7: 12,0 | E7: — | F7: =SUM(CHK!B2:B201) | G7: =COUNTBLANK('SECCION_1_LID'!B2:B201)
A8: 3 | B8: MONEDA | C8: TEXTO | D8: 3 | E8: Moneda | F8: =SUM(CHK!C2:C201) | G8: =COUNTBLANK('SECCION_1_LID'!C2:C201)
A9: 4 | B9: FECHA_INFO | C9: FECHA | D9: AAAA/MM/DD | E9: — | F9: =SUM(CHK!D2:D201) | G9: =COUNTBLANK('SECCION_1_LID'!D2:D201)

Sheet SECCION_1_LID
A1: TIPO_ACTIVO | B1: SALDO_ID | C1: MONEDA | D1: FECHA_INFO

Sheet CAT_TIPO_ACTIVO_LID
A1: Clave | B1: Descripcion
A2: 1 | B2: Depositos de regulacion monetaria
A3: 10 | B3: Colateral disponible del otorgado en garanti´a en mercados reconocidos que puede ser utilizado para la liquidacio´n de operaciones intradi´a
A4: 11 | B4: Colateral disponible del otorgado en garanti´a en mercados no reconocidos que puede ser utilizado para la liquidacio´n de operaciones intradi´a
A5: 12 | B5: Lineas de credito disponibles en el itradia
A6: 13 | B6: Depositos en otros bancos
A7: 14 | B7: Otros activos que puedan utilizarse para liquidacion
A8: 2 | B8: Depositos constituidos por Operaciones de Mercado Abierto (OMA)
A9: 3 | B9: Depositos constituidos para determinacion de la Tasa de Interes Interbancaria de Equilibrio (TIIE)
A10: 4 | B10: Saldo de la cuenta unica
A11: 5 | B11: Depositos correspondientes al Sistema de Pagos Interbancarios en dolares (SPID)
A12: 6 | B12: Depositos en dolares de los Estados Unidos de America (EUA)
... A15: 9 | B15: Colateral disponible del otorgado en garantia en otros sistemas de pago (sistemas de pago minorista, CLS, sistemas de liquidacion de valores y las contrapartes centrales) que puede ser utilizado para la liquidacion de operaciones intradia

Sheet CAT_MONEDA
A1: Clave | B1: Descripcion
A2: AFN | B2: 971
A3: EUR | B3: 978
A4: ALL | B4: 8
A5: DZD | B5: 12
A6: USD | B6: 840
A7: AOA | B7: 973
A8: XCD | B8: 951
A9: ARS | B9: 32
A10: AMD | B10: 51
A11: AWG | B11: 533
A12: AUD | B12: 36
... A171: ZWL | B171: 932

Sheet CHK
A2: =IF(AND('SECCION_1_LID'!A2<>"",COUNTIF(CL_TIPO_ACTIVO_LID,'SECCION_1_LID'!A2)=0),1,0) | B2: =IF(AND('SECCION_1_LID'!B2<>"",IF(ISNUMBER('SECCION_1_LID'!B2),OR('SECCION_1_LID'!B2<>ROUND('SECCION_1_LID'!B2,0),LEN(TEXT(INT(ABS('SECCION_1_LID'!B2)),"0"))>12),TRUE)),1,0) | C2: =IF(AND('SECCION_1_LID'!C2<>"",OR(LEN('SECCION_1_LID'!C2)>3,COUNTIF(CL_MONEDA,'SECCION_1_LID'!C2)=0)),1,0) | D2: =IF(AND('SECCION_1_LID'!D2<>"",NOT(ISNUMBER('SECCION_1_LID'!D2))),1,0)
A3: =IF(AND('SECCION_1_LID'!A3<>"",COUNTIF(CL_TIPO_ACTIVO_LID,'SECCION_1_LID'!A3)=0),1,0) | B3: =IF(AND('SECCION_1_LID'!B3<>"",IF(ISNUMBER('SECCION_1_LID'!B3),OR('SECCION_1_LID'!B3<>ROUND('SECCION_1_LID'!B3,0),LEN(TEXT(INT(ABS('SECCION_1_LID'!B3)),"0"))>12),TRUE)),1,0) | C3: =IF(AND('SECCION_1_LID'!C3<>"",OR(LEN('SECCION_1_LID'!C3)>3,COUNTIF(CL_MONEDA,'SECCION_1_LID'!C3)=0)),1,0) | D3: =IF(AND('SECCION_1_LID'!D3<>"",NOT(ISNUMBER('SECCION_1_LID'!D3))),1,0)
A4: =IF(AND('SECCION_1_LID'!A4<>"",COUNTIF(CL_TIPO_ACTIVO_LID,'SECCION_1_LID'!A4)=0),1,0) | B4: =IF(AND('SECCION_1_LID'!B4<>"",IF(ISNUMBER('SECCION_1_LID'!B4),OR('SECCION_1_LID'!B4<>ROUND('SECCION_1_LID'!B4,0),LEN(TEXT(INT(ABS('SECCION_1_LID'!B4)),"0"))>12),TRUE)),1,0) | C4: =IF(AND('SECCION_1_LID'!C4<>"",OR(LEN('SECCION_1_LID'!C4)>3,COUNTIF(CL_MONEDA,'SECCION_1_LID'!C4)=0)),1,0) | D4: =IF(AND('SECCION_1_LID'!D4<>"",NOT(ISNUMBER('SECCION_1_LID'!D4))),1,0)
A5: =IF(AND('SECCION_1_LID'!A5<>"",COUNTIF(CL_TIPO_ACTIVO_LID,'SECCION_1_LID'!A5)=0),1,0) | B5: =IF(AND('SECCION_1_LID'!B5<>"",IF(ISNUMBER('SECCION_1_LID'!B5),OR('SECCION_1_LID'!B5<>ROUND('SECCION_1_LID'!B5,0),LEN(TEXT(INT(ABS('SECCION_1_LID'!B5)),"0"))>12),TRUE)),1,0) | C5: =IF(AND('SECCION_1_LID'!C5<>"",OR(LEN('SECCION_1_LID'!C5)>3,COUNTIF(CL_MONEDA,'SECCION_1_LID'!C5)=0)),1,0) | D5: =IF(AND('SECCION_1_LID'!D5<>"",NOT(ISNUMBER('SECCION_1_LID'!D5))),1,0)
A6: =IF(AND('SECCION_1_LID'!A6<>"",COUNTIF(CL_TIPO_ACTIVO_LID,'SECCION_1_LID'!A6)=0),1,0) | B6: =IF(AND('SECCION_1_LID'!B6<>"",IF(ISNUMBER('SECCION_1_LID'!B6),OR('SECCION_1_LID'!B6<>ROUND('SECCION_1_LID'!B6,0),LEN(TEXT(INT(ABS('SECCION_1_LID'!B6)),"0"))>12),TRUE)),1,0) | C6: =IF(AND('SECCION_1_LID'!C6<>"",OR(LEN('SECCION_1_LID'!C6)>3,COUNTIF(CL_MONEDA,'SECCION_1_LID'!C6)=0)),1,0) | D6: =IF(AND('SECCION_1_LID'!D6<>"",NOT(ISNUMBER('SECCION_1_LID'!D6))),1,0)
A7: =IF(AND('SECCION_1_LID'!A7<>"",COUNTIF(CL_TIPO_ACTIVO_LID,'SECCION_1_LID'!A7)=0),1,0) | B7: =IF(AND('SECCION_1_LID'!B7<>"",IF(ISNUMBER('SECCION_1_LID'!B7),OR('SECCION_1_LID'!B7<>ROUND('SECCION_1_LID'!B7,0),LEN(TEXT(INT(ABS('SECCION_1_LID'!B7)),"0"))>12),TRUE)),1,0) | C7: =IF(AND('SECCION_1_LID'!C7<>"",OR(LEN('SECCION_1_LID'!C7)>3,COUNTIF(CL_MONEDA,'SECCION_1_LID'!C7)=0)),1,0) | D7: =IF(AND('SECCION_1_LID'!D7<>"",NOT(ISNUMBER('SECCION_1_LID'!D7))),1,0)
A8: =IF(AND('SECCION_1_LID'!A8<>"",COUNTIF(CL_TIPO_ACTIVO_LID,'SECCION_1_LID'!A8)=0),1,0) | B8: =IF(AND('SECCION_1_LID'!B8<>"",IF(ISNUMBER('SECCION_1_LID'!B8),OR('SECCION_1_LID'!B8<>ROUND('SECCION_1_LID'!B8,0),LEN(TEXT(INT(ABS('SECCION_1_LID'!B8)),"0"))>12),TRUE)),1,0) | C8: =IF(AND('SECCION_1_LID'!C8<>"",OR(LEN('SECCION_1_LID'!C8)>3,COUNTIF(CL_MONEDA,'SECCION_1_LID'!C8)=0)),1,0) | D8: =IF(AND('SECCION_1_LID'!D8<>"",NOT(ISNUMBER('SECCION_1_LID'!D8))),1,0)
A9: =IF(AND('SECCION_1_LID'!A9<>"",COUNTIF(CL_TIPO_ACTIVO_LID,'SECCION_1_LID'!A9)=0),1,0) | B9: =IF(AND('SECCION_1_LID'!B9<>"",IF(ISNUMBER('SECCION_1_LID'!B9),OR('SECCION_1_LID'!B9<>ROUND('SECCION_1_LID'!B9,0),LEN(TEXT(INT(ABS('SECCION_1_LID'!B9)),"0"))>12),TRUE)),1,0) | C9: =IF(AND('SECCION_1_LID'!C9<>"",OR(LEN('SECCION_1_LID'!C9)>3,COUNTIF(CL_MONEDA,'SECCION_1_LID'!C9)=0)),1,0) | D9: =IF(AND('SECCION_1_LID'!D9<>"",NOT(ISNUMBER('SECCION_1_LID'!D9))),1,0)
A10: =IF(AND('SECCION_1_LID'!A10<>"",COUNTIF(CL_TIPO_ACTIVO_LID,'SECCION_1_LID'!A10)=0),1,0) | B10: =IF(AND('SECCION_1_LID'!B10<>"",IF(ISNUMBER('SECCION_1_LID'!B10),OR('SECCION_1_LID'!B10<>ROUND('SECCION_1_LID'!B10,0),LEN(TEXT(INT(ABS('SECCION_1_LID'!B10)),"0"))>12),TRUE)),1,0) | C10: =IF(AND('SECCION_1_LID'!C10<>"",OR(LEN('SECCION_1_LID'!C10)>3,COUNTIF(CL_MONEDA,'SECCION_1_LID'!C10)=0)),1,0) | D10: =IF(AND('SECCION_1_LID'!D10<>"",NOT(ISNUMBER('SECCION_1_LID'!D10))),1,0)
A11: =IF(AND('SECCION_1_LID'!A11<>"",COUNTIF(CL_TIPO_ACTIVO_LID,'SECCION_1_LID'!A11)=0),1,0) | B11: =IF(AND('SECCION_1_LID'!B11<>"",IF(ISNUMBER('SECCION_1_LID'!B11),OR('SECCION_1_LID'!B11<>ROUND('SECCION_1_LID'!B11,0),LEN(TEXT(INT(ABS('SECCION_1_LID'!B11)),"0"))>12),TRUE)),1,0) | C11: =IF(AND('SECCION_1_LID'!C11<>"",OR(LEN('SECCION_1_LID'!C11)>3,COUNTIF(CL_MONEDA,'SECCION_1_LID'!C11)=0)),1,0) | D11: =IF(AND('SECCION_1_LID'!D11<>"",NOT(ISNUMBER('SECCION_1_LID'!D11))),1,0)
A12: =IF(AND('SECCION_1_LID'!A12<>"",COUNTIF(CL_TIPO_ACTIVO_LID,'SECCION_1_LID'!A12)=0),1,0) | B12: =IF(AND('SECCION_1_LID'!B12<>"",IF(ISNUMBER('SECCION_1_LID'!B12),OR('SECCION_1_LID'!B12<>ROUND('SECCION_1_LID'!B12,0),LEN(TEXT(INT(ABS('SECCION_1_LID'!B12)),"0"))>12),TRUE)),1,0) | C12: =IF(AND('SECCION_1_LID'!C12<>"",OR(LEN('SECCION_1_LID'!C12)>3,COUNTIF(CL_MONEDA,'SECCION_1_LID'!C12)=0)),1,0) | D12: =IF(AND('SECCION_1_LID'!D12<>"",NOT(ISNUMBER('SECCION_1_LID'!D12))),1,0)
A13: =IF(AND('SECCION_1_LID'!A13<>"",COUNTIF(CL_TIPO_ACTIVO_LID,'SECCION_1_LID'!A13)=0),1,0) | B13: =IF(AND('SECCION_1_LID'!B13<>"",IF(ISNUMBER('SECCION_1_LID'!B13),OR('SECCION_1_LID'!B13<>ROUND('SECCION_1_LID'!B13,0),LEN(TEXT(INT(ABS('SECCION_1_LID'!B13)),"0"))>12),TRUE)),1,0) | C13: =IF(AND('SECCION_1_LID'!C13<>"",OR(LEN('SECCION_1_LID'!C13)>3,COUNTIF(CL_MONEDA,'SECCION_1_LID'!C13)=0)),1,0) | D13: =IF(AND('SECCION_1_LID'!D13<>"",NOT(ISNUMBER('SECCION_1_LID'!D13))),1,0)
... A201: =IF(AND('SECCION_1_LID'!A201<>"",COUNTIF(CL_TIPO_ACTIVO_LID,'SECCION_1_LID'!A201)=0),1,0) | B201: =IF(AND('SECCION_1_LID'!B201<>"",IF(ISNUMBER('SECCION_1_LID'!B201),OR('SECCION_1_LID'!B201<>ROUND('SECCION_1_LID'!B201,0),LEN(TEXT(INT(ABS('SECCION_1_LID'!B201)),"0"))>12),TRUE)),1,0) | C201: =IF(AND('SECCION_1_LID'!C201<>"",OR(LEN('SECCION_1_LID'!C201)>3,COUNTIF(CL_MONEDA,'SECCION_1_LID'!C201)=0)),1,0) | D201: =IF(AND('SECCION_1_LID'!D201<>"",NOT(ISNUMBER('SECCION_1_LID'!D201))),1,0)
