Workbook
Name CL_POSICIONOPERACION_V4: CAT_POSICIONOPERACION_V4!$A$2:$A$3
Name CL_OBJ_OPE_V1: CAT_OBJ_OPE_V1!$A$2:$A$8
Name CL_PAQ_EST_DER_V1: CAT_PAQ_EST_DER_V1!$A$2:$A$40
Name CL_MONEDAISO: CAT_MONEDAISO!$A$2:$A$190

Sheet VALIDACION
A1: RESUMEN DE VALIDACIÓN
A2: Total celdas con error de formato: | C2: =SUM(CHK!A2:Q201)
A3: Estado: | C3: =IF(C2=0,"✔ SIN ERRORES DE FORMATO","✖ REVISAR: "&C2&" celda(s) marcada(s) en rojo")
A5: Orden | B5: Campo | C5: Tipo | D5: Long | E5: Catálogo | F5: # Errores | G5: # Vacíos (obligatorio)
A6: 1 | B6: FE_CON_OPE | C6: FECHA | D6: AAAA/MM/DD | E6: — | F6: =SUM(CHK!A2:A201) | G6: =COUNTBLANK('OFF_CONVAL'!A2:A201)
A7: 2 | B7: NUM_ID | C7: TEXTO | D7: 20 | E7: — | F7: =SUM(CHK!B2:B201) | G7: =COUNTBLANK('OFF_CONVAL'!B2:B201)
A8: 3 | B8: POS_OPER | C8: TEXTO | D8: 1 | E8: PosicionOperacion_V4 | F8: =SUM(CHK!C2:C201) | G8: =COUNTBLANK('OFF_CONVAL'!C2:C201)
A9: 4 | B9: OBJ_OPE | C9: TEXTO | D9: 2 | E9: OBJ_OPE_V1 | F9: =SUM(CHK!D2:D201) | G9: =COUNTBLANK('OFF_CONVAL'!D2:D201)
A10: 5 | B10: PAQ_EST | C10: NUMERICO | D10: 2 | E10: PAQ_EST_DER_V1 | F10: =SUM(CHK!E2:E201) | G10: =COUNTBLANK('OFF_CONVAL'!E2:E201)
A11: 6 | B11: ID_PAQ_EST | C11: TEXTO | D11: 20 | E11: — | F11: =SUM(CHK!F2:F201) | G11: =COUNTBLANK('OFF_CONVAL'!F2:F201)
A12: 7 | B12: CON_PAQ_EST | C12: NUMERICO | D12: 3 | E12: — | F12: =SUM(CHK!G2:G201) | G12: =COUNTBLANK('OFF_CONVAL'!G2:G201)
A13: 8 | B13: ACT_OPE | C13: NUMERICO | D13: 15 | E13: — | F13: =SUM(CHK!H2:H201) | G13: =COUNTBLANK('OFF_CONVAL'!H2:H201)
A14: 9 | B14: MON_ACT_OPE | C14: TEXTO | D14: 3 | E14: MonedaISO | F14: =SUM(CHK!I2:I201) | G14: =COUNTBLANK('OFF_CONVAL'!I2:I201)
A15: 10 | B15: PAS_OPE | C15: NUMERICO | D15: 15 | E15: — | F15: =SUM(CHK!J2:J201) | G15: =COUNTBLANK('OFF_CONVAL'!J2:J201)
A16: 11 | B16: MON_PAS_OPE | C16: TEXTO | D16: 3 | E16: MonedaISO | F16: =SUM(CHK!K2:K201) | G16: =COUNTBLANK('OFF_CONVAL'!K2:K201)
A17: 12 | B17: DUR_ACT | C17: NUMERICO | D17: 5 | E17: — | F17: =SUM(CHK!L2:L201) | G17: =COUNTBLANK('OFF_CONVAL'!L2:L201)
A18: 13 | B18: DUR_PAS | C18: NUMERICO | D18: 5 | E18: — | F18: =SUM(CHK!M2:M201) | G18: =COUNTBLANK('OFF_CONVAL'!M2:M201)
A19: 14 | B19: ID_GAR_VG | C19: TEXTO | D19: 20 | E19: — | F19: =SUM(CHK!N2:N201) | G19: =COUNTBLANK('OFF_CONVAL'!N2:N201)
A20: 15 | B20: NOCIONAL | C20: NUMERICO | D20: 15 | E20: — | F20: =SUM(CHK!O2:O201) | G20: =COUNTBLANK('OFF_CONVAL'!O2:O201)
A21: 16 | B21: MON_NOCIONAL | C21: TEXTO | D21: 3 | E21: MonedaISO | F21: =SUM(CHK!P2:P201) | G21: =COUNTBLANK('OFF_CONVAL'!P2:P201)
A22: 17 | B22: FECHAINFO | C22: FECHA | D22: AAAA/MM/DD | E22: — | F22: =SUM(CHK!Q2:Q201) | G22: =COUNTBLANK('OFF_CONVAL'!Q2:Q201)

Sheet OFF_CONVAL
A1: FE_CON_OPE | B1: NUM_ID | C1: POS_OPER | D1: OBJ_OPE | E1: PAQ_EST | F1: ID_PAQ_EST | G1: CON_PAQ_EST | H1: ACT_OPE | I1: MON_ACT_OPE | J1: PAS_OPE | K1: MON_PAS_OPE | L1: DUR_ACT | M1: DUR_PAS | N1: ID_GAR_VG | O1: NOCIONAL | P1: MON_NOCIONAL | Q1: FECHAINFO

Sheet CAT_POSICIONOPERACION_V4
A1: Clave | B1: Descripcion
A2: C | B2: OPERACIONES DE COMPRA EN DIRECTO
A3: V | B3: OPERACIONES DE VENTA EN DIRECTO

Sheet CAT_OBJ_OPE_V1
A1: Clave | B1: Descripcion
A2: NE | B2: Cuando la Institución celebre la operación con el objetivo de "Negociación".
A3: CC | B3: Cuando la Institución celebre la operación con el objetivo de "Cobertura" para su cartera de créditos (incluye consumo, comercial y vivenda).
A4: CT | B4: Cuando la Institución celebre la operación con el objetivo de "Cobertura" para su portafolio de títulos de deuda (diferentes a títulos opcionales).
A5: CW | B5: Cuando la Institución celebre la operación con el objetivo de "Cobertura" para su portafolio de títulos opcionales ("Warrants").
A6: CA | B6: Cuando la Institución celebre la operación con el objetivo de "Cobertura" para otros activos distintos a créditos, títulos de deuda y títulos opcionales.
A7: CP | B7: Cuando la Institución celebre la operación con el objetivo de "Cobertura" de algún pasivo (incluye la emisión de títulos de deuda o títlos opcionales).
A8: JP | B8: En operaciones realizadas por la Institución para su Fondo de Reservas para Pensiones, Jubilaciones y demás Prestaciones al personal; cuando dicho Fondo forme parte del Balance de la Institución.

Sheet CAT_PAQ_EST_DER_V1
A1: Clave | B1: Descripcion
A2: 1 | B2: Paquete de opciones de compra de tasas de interés, con fechas de vencimiento sucesivas ("Caps")
A3: 2 | B3: Paquete de opciones de venta de tasas de interés, con fechas de vencimiento sucesivas ("Floors")
A4: 3 | B4: Paquete de opciones de compra sobre subyacentes distintos a tasas de interés
A5: 4 | B5: Paquete de opciones de venta sobre subyacentes distintos a tasas de interés
A6: 5 | B6: Paquete de opciones binarias o digitales (conocidos como "Corridor")
A7: 6 | B7: Swaption (opción cuyo subyacente es un contrato de intercambio de flujos y rendimientos o "Swap")
A8: 7 | B8: Opciones sobre forwards (contrato de opción cuyo subyacente es un contrato adelantado o "forward")
A9: 8 | B9: Opción de una barrera (La opción se activa o extingue, si el precio de mercado del subyacentes es igual o supera un nivel predeterminado)
A10: 9 | B10: Opción de doble barrera (La opción se activa o extingue, si el precio de mercado del subyacentes rebasa o no alguno de los 2 niveles predeterminados)
A11: 10 | B11: Opción tipo "Lookback maxmin" (El precio de ejercicio es el mayor o menor observado durante la vigencia de la operación)
A12: 11 | B12: Opción tipo "Lookback avg" (El precio de ejercicio resulta del promedio de los precios observados durante la vigencia de la operación)
... A40: 90 | B40: No aplica; es decir, la operación o contrato es convencional o simple (plain vainilla), y no esta comprendido en algún paquete o estrategia de este catálogo

Sheet CAT_MONEDAISO
A1: Clave | B1: Descripcion
A2: AED | B2: UAE Dirham
A3: AFN | B3: Afghani
A4: ALL | B4: Lek
A5: AMD | B5: Armenian Dram
A6: ANG | B6: Netherlands Antillean Guilder
A7: AOA | B7: Kwanza
A8: ARS | B8: Argentine Peso
A9: AUD | B9: Australian Dollar
A10: AWG | B10: Aruban Guilder
A11: AZN | B11: Azerbaijanian Manat
A12: BAM | B12: Convertible Mark
... A190: ZMW | B190: Kwacha zambiano

Sheet CHK
A2: =IF(AND('OFF_CONVAL'!A2<>"",NOT(ISNUMBER('OFF_CONVAL'!A2))),1,0) | B2: =IF(AND('OFF_CONVAL'!B2<>"",LEN('OFF_CONVAL'!B2)>20),1,0) | C2: =IF(AND('OFF_CONVAL'!C2<>"",OR(LEN('OFF_CONVAL'!C2)>1,COUNTIF(CL_POSICIONOPERACION_V4,'OFF_CONVAL'!C2)=0)),1,0) | D2: =IF(AND('OFF_CONVAL'!D2<>"",OR(LEN('OFF_CONVAL'!D2)>2,COUNTIF(CL_OBJ_OPE_V1,'OFF_CONVAL'!D2)=0)),1,0) | E2: =IF(AND('OFF_CONVAL'!E2<>"",COUNTIF(CL_PAQ_EST_DER_V1,'OFF_CONVAL'!E2)=0),1,0) | F2: =IF(AND('OFF_CONVAL'!F2<>"",LEN('OFF_CONVAL'!F2)>20),1,0) | G2: =IF(AND('OFF_CONVAL'!G2<>"",IF(ISNUMBER('OFF_CONVAL'!G2),OR('OFF_CONVAL'!G2<>INT('OFF_CONVAL'!G2),LEN(TEXT(ABS('OFF_CONVAL'!G2),"0"))>3),TRUE)),1,0) | H2: =IF(AND('OFF_CONVAL'!H2<>"",IF(ISNUMBER('OFF_CONVAL'!H2),OR('OFF_CONVAL'!H2<>INT('OFF_CONVAL'!H2),LEN(TEXT(ABS('OFF_CONVAL'!H2),"0"))>15),TRUE)),1,0) | I2: =IF(AND('OFF_CONVAL'!I2<>"",OR(LEN('OFF_CONVAL'!I2)>3,COUNTIF(CL_MONEDAISO,'OFF_CONVAL'!I2)=0)),1,0) | J2: =IF(AND('OFF_CONVAL'!J2<>"",IF(ISNUMBER('OFF_CONVAL'!J2),OR('OFF_CONVAL'!J2<>INT('OFF_CONVAL'!J2),LEN(TEXT(ABS('OFF_CONVAL'!J2),"0"))>15),TRUE)),1,0) | K2: =IF(AND('OFF_CONVAL'!K2<>"",OR(LEN('OFF_CONVAL'!K2)>3,COUNTIF(CL_MONEDAISO,'OFF_CONVAL'!K2)=0)),1,0) | L2: =IF(AND('OFF_CONVAL'!L2<>"",IF(ISNUMBER('OFF_CONVAL'!L2),OR('OFF_CONVAL'!L2<>INT('OFF_CONVAL'!L2),LEN(TEXT(ABS('OFF_CONVAL'!L2),"0"))>5),TRUE)),1,0) | M2: =IF(AND('OFF_CONVAL'!M2<>"",IF(ISNUMBER('OFF_CONVAL'!M2),OR('OFF_CONVAL'!M2<>INT('OFF_CONVAL'!M2),LEN(TEXT(ABS('OFF_CONVAL'!M2),"0"))>5),TRUE)),1,0) | N2: =IF(AND('OFF_CONVAL'!N2<>"",LEN('OFF_CONVAL'!N2)>20),1,0) | O2: =IF(AND('OFF_CONVAL'!O2<>"",IF(ISNUMBER('OFF_CONVAL'!O2),OR('OFF_CONVAL'!O2<>INT('OFF_CONVAL'!O2),LEN(TEXT(ABS('OFF_CONVAL'!O2),"0"))>15),TRUE)),1,0) | P2: =IF(AND('OFF_CONVAL'!P2<>"",OR(LEN('OFF_CONVAL'!P2)>3,COUNTIF(CL_MONEDAISO,'OFF_CONVAL'!P2)=0)),1,0) | Q2: =IF(AND('OFF_CONVAL'!Q2<>"",NOT(ISNUMBER('OFF_CONVAL'!Q2))),1,0)
A3: =IF(AND('OFF_CONVAL'!A3<>"",NOT(ISNUMBER('OFF_CONVAL'!A3))),1,0) | B3: =IF(AND('OFF_CONVAL'!B3<>"",LEN('OFF_CONVAL'!B3)>20),1,0) | C3: =IF(AND('OFF_CONVAL'!C3<>"",OR(LEN('OFF_CONVAL'!C3)>1,COUNTIF(CL_POSICIONOPERACION_V4,'OFF_CONVAL'!C3)=0)),1,0) | D3: =IF(AND('OFF_CONVAL'!D3<>"",OR(LEN('OFF_CONVAL'!D3)>2,COUNTIF(CL_OBJ_OPE_V1,'OFF_CONVAL'!D3)=0)),1,0) | E3: =IF(AND('OFF_CONVAL'!E3<>"",COUNTIF(CL_PAQ_EST_DER_V1,'OFF_CONVAL'!E3)=0),1,0) | F3: =IF(AND('OFF_CONVAL'!F3<>"",LEN('OFF_CONVAL'!F3)>20),1,0) | G3: =IF(AND('OFF_CONVAL'!G3<>"",IF(ISNUMBER('OFF_CONVAL'!G3),OR('OFF_CONVAL'!G3<>INT('OFF_CONVAL'!G3),LEN(TEXT(ABS('OFF_CONVAL'!G3),"0"))>3),TRUE)),1,0) | H3: =IF(AND('OFF_CONVAL'!H3<>"",IF(ISNUMBER('OFF_CONVAL'!H3),OR('OFF_CONVAL'!H3<>INT('OFF_CONVAL'!H3),LEN(TEXT(ABS('OFF_CONVAL'!H3),"0"))>15),TRUE)),1,0) | I3: =IF(AND('OFF_CONVAL'!I3<>"",OR(LEN('OFF_CONVAL'!I3)>3,COUNTIF(CL_MONEDAISO,'OFF_CONVAL'!I3)=0)),1,0) | J3: =IF(AND('OFF_CONVAL'!J3<>"",IF(ISNUMBER('OFF_CONVAL'!J3),OR('OFF_CONVAL'!J3<>INT('OFF_CONVAL'!J3),LEN(TEXT(ABS('OFF_CONVAL'!J3),"0"))>15),TRUE)),1,0) | K3: =IF(AND('OFF_CONVAL'!K3<>"",OR(LEN('OFF_CONVAL'!K3)>3,COUNTIF(CL_MONEDAISO,'OFF_CONVAL'!K3)=0)),1,0) | L3: =IF(AND('OFF_CONVAL'!L3<>"",IF(ISNUMBER('OFF_CONVAL'!L3),OR('OFF_CONVAL'!L3<>INT('OFF_CONVAL'!L3),LEN(TEXT(ABS('OFF_CONVAL'!L3),"0"))>5),TRUE)),1,0) | M3: =IF(AND('OFF_CONVAL'!M3<>"",IF(ISNUMBER('OFF_CONVAL'!M3),OR('OFF_CONVAL'!M3<>INT('OFF_CONVAL'!M3),LEN(TEXT(ABS('OFF_CONVAL'!M3),"0"))>5),TRUE)),1,0) | N3: =IF(AND('OFF_CONVAL'!N3<>"",LEN('OFF_CONVAL'!N3)>20),1,0) | O3: =IF(AND('OFF_CONVAL'!O3<>"",IF(ISNUMBER('OFF_CONVAL'!O3),OR('OFF_CONVAL'!O3<>INT('OFF_CONVAL'!O3),LEN(TEXT(ABS('OFF_CONVAL'!O3),"0"))>15),TRUE)),1,0) | P3: =IF(AND('OFF_CONVAL'!P3<>"",OR(LEN('OFF_CONVAL'!P3)>3,COUNTIF(CL_MONEDAISO,'OFF_CONVAL'!P3)=0)),1,0) | Q3: =IF(AND('OFF_CONVAL'!Q3<>"",NOT(ISNUMBER('OFF_CONVAL'!Q3))),1,0)
A4: =IF(AND('OFF_CONVAL'!A4<>"",NOT(ISNUMBER('OFF_CONVAL'!A4))),1,0) | B4: =IF(AND('OFF_CONVAL'!B4<>"",LEN('OFF_CONVAL'!B4)>20),1,0) | C4: =IF(AND('OFF_CONVAL'!C4<>"",OR(LEN('OFF_CONVAL'!C4)>1,COUNTIF(CL_POSICIONOPERACION_V4,'OFF_CONVAL'!C4)=0)),1,0) | D4: =IF(AND('OFF_CONVAL'!D4<>"",OR(LEN('OFF_CONVAL'!D4)>2,COUNTIF(CL_OBJ_OPE_V1,'OFF_CONVAL'!D4)=0)),1,0) | E4: =IF(AND('OFF_CONVAL'!E4<>"",COUNTIF(CL_PAQ_EST_DER_V1,'OFF_CONVAL'!E4)=0),1,0) | F4: =IF(AND('OFF_CONVAL'!F4<>"",LEN('OFF_CONVAL'!F4)>20),1,0) | G4: =IF(AND('OFF_CONVAL'!G4<>"",IF(ISNUMBER('OFF_CONVAL'!G4),OR('OFF_CONVAL'!G4<>INT('OFF_CONVAL'!G4),LEN(TEXT(ABS('OFF_CONVAL'!G4),"0"))>3),TRUE)),1,0) | H4: =IF(AND('OFF_CONVAL'!H4<>"",IF(ISNUMBER('OFF_CONVAL'!H4),OR('OFF_CONVAL'!H4<>INT('OFF_CONVAL'!H4),LEN(TEXT(ABS('OFF_CONVAL'!H4),"0"))>15),TRUE)),1,0) | I4: =IF(AND('OFF_CONVAL'!I4<>"",OR(LEN('OFF_CONVAL'!I4)>3,COUNTIF(CL_MONEDAISO,'OFF_CONVAL'!I4)=0)),1,0) | J4: =IF(AND('OFF_CONVAL'!J4<>"",IF(ISNUMBER('OFF_CONVAL'!J4),OR('OFF_CONVAL'!J4<>INT('OFF_CONVAL'!J4),LEN(TEXT(ABS('OFF_CONVAL'!J4),"0"))>15),TRUE)),1,0) | K4: =IF(AND('OFF_CONVAL'!K4<>"",OR(LEN('OFF_CONVAL'!K4)>3,COUNTIF(CL_MONEDAISO,'OFF_CONVAL'!K4)=0)),1,0) | L4: =IF(AND('OFF_CONVAL'!L4<>"",IF(ISNUMBER('OFF_CONVAL'!L4),OR('OFF_CONVAL'!L4<>INT('OFF_CONVAL'!L4),LEN(TEXT(ABS('OFF_CONVAL'!L4),"0"))>5),TRUE)),1,0) | M4: =IF(AND('OFF_CONVAL'!M4<>"",IF(ISNUMBER('OFF_CONVAL'!M4),OR('OFF_CONVAL'!M4<>INT('OFF_CONVAL'!M4),LEN(TEXT(ABS('OFF_CONVAL'!M4),"0"))>5),TRUE)),1,0) | N4: =IF(AND('OFF_CONVAL'!N4<>"",LEN('OFF_CONVAL'!N4)>20),1,0) | O4: =IF(AND('OFF_CONVAL'!O4<>"",IF(ISNUMBER('OFF_CONVAL'!O4),OR('OFF_CONVAL'!O4<>INT('OFF_CONVAL'!O4),LEN(TEXT(ABS('OFF_CONVAL'!O4),"0"))>15),TRUE)),1,0) | P4: =IF(AND('OFF_CONVAL'!P4<>"",OR(LEN('OFF_CONVAL'!P4)>3,COUNTIF(CL_MONEDAISO,'OFF_CONVAL'!P4)=0)),1,0) | Q4: =IF(AND('OFF_CONVAL'!Q4<>"",NOT(ISNUMBER('OFF_CONVAL'!Q4))),1,0)
A5: =IF(AND('OFF_CONVAL'!A5<>"",NOT(ISNUMBER('OFF_CONVAL'!A5))),1,0) | B5: =IF(AND('OFF_CONVAL'!B5<>"",LEN('OFF_CONVAL'!B5)>20),1,0) | C5: =IF(AND('OFF_CONVAL'!C5<>"",OR(LEN('OFF_CONVAL'!C5)>1,COUNTIF(CL_POSICIONOPERACION_V4,'OFF_CONVAL'!C5)=0)),1,0) | D5: =IF(AND('OFF_CONVAL'!D5<>"",OR(LEN('OFF_CONVAL'!D5)>2,COUNTIF(CL_OBJ_OPE_V1,'OFF_CONVAL'!D5)=0)),1,0) | E5: =IF(AND('OFF_CONVAL'!E5<>"",COUNTIF(CL_PAQ_EST_DER_V1,'OFF_CONVAL'!E5)=0),1,0) | F5: =IF(AND('OFF_CONVAL'!F5<>"",LEN('OFF_CONVAL'!F5)>20),1,0) | G5: =IF(AND('OFF_CONVAL'!G5<>"",IF(ISNUMBER('OFF_CONVAL'!G5),OR('OFF_CONVAL'!G5<>INT('OFF_CONVAL'!G5),LEN(TEXT(ABS('OFF_CONVAL'!G5),"0"))>3),TRUE)),1,0) | H5: =IF(AND('OFF_CONVAL'!H5<>"",IF(ISNUMBER('OFF_CONVAL'!H5),OR('OFF_CONVAL'!H5<>INT('OFF_CONVAL'!H5),LEN(TEXT(ABS('OFF_CONVAL'!H5),"0"))>15),TRUE)),1,0) | I5: =IF(AND('OFF_CONVAL'!I5<>"",OR(LEN('OFF_CONVAL'!I5)>3,COUNTIF(CL_MONEDAISO,'OFF_CONVAL'!I5)=0)),1,0) | J5: =IF(AND('OFF_CONVAL'!J5<>"",IF(ISNUMBER('OFF_CONVAL'!J5),OR('OFF_CONVAL'!J5<>INT('OFF_CONVAL'!J5),LEN(TEXT(ABS('OFF_CONVAL'!J5),"0"))>15),TRUE)),1,0) | K5: =IF(AND('OFF_CONVAL'!K5<>"",OR(LEN('OFF_CONVAL'!K5)>3,COUNTIF(CL_MONEDAISO,'OFF_CONVAL'!K5)=0)),1,0) | L5: =IF(AND('OFF_CONVAL'!L5<>"",IF(ISNUMBER('OFF_CONVAL'!L5),OR('OFF_CONVAL'!L5<>INT('OFF_CONVAL'!L5),LEN(TEXT(ABS('OFF_CONVAL'!L5),"0"))>5),TRUE)),1,0) | M5: =IF(AND('OFF_CONVAL'!M5<>"",IF(ISNUMBER('OFF_CONVAL'!M5),OR('OFF_CONVAL'!M5<>INT('OFF_CONVAL'!M5),LEN(TEXT(ABS('OFF_CONVAL'!M5),"0"))>5),TRUE)),1,0) | N5: =IF(AND('OFF_CONVAL'!N5<>"",LEN('OFF_CONVAL'!N5)>20),1,0) | O5: =IF(AND('OFF_CONVAL'!O5<>"",IF(ISNUMBER('OFF_CONVAL'!O5),OR('OFF_CONVAL'!O5<>INT('OFF_CONVAL'!O5),LEN(TEXT(ABS('OFF_CONVAL'!O5),"0"))>15),TRUE)),1,0) | P5: =IF(AND('OFF_CONVAL'!P5<>"",OR(LEN('OFF_CONVAL'!P5)>3,COUNTIF(CL_MONEDAISO,'OFF_CONVAL'!P5)=0)),1,0) | Q5: =IF(AND('OFF_CONVAL'!Q5<>"",NOT(ISNUMBER('OFF_CONVAL'!Q5))),1,0)
A6: =IF(AND('OFF_CONVAL'!A6<>"",NOT(ISNUMBER('OFF_CONVAL'!A6))),1,0) | B6: =IF(AND('OFF_CONVAL'!B6<>"",LEN('OFF_CONVAL'!B6)>20),1,0) | C6: =IF(AND('OFF_CONVAL'!C6<>"",OR(LEN('OFF_CONVAL'!C6)>1,COUNTIF(CL_POSICIONOPERACION_V4,'OFF_CONVAL'!C6)=0)),1,0) | D6: =IF(AND('OFF_CONVAL'!D6<>"",OR(LEN('OFF_CONVAL'!D6)>2,COUNTIF(CL_OBJ_OPE_V1,'OFF_CONVAL'!D6)=0)),1,0) | E6: =IF(AND('OFF_CONVAL'!E6<>"",COUNTIF(CL_PAQ_EST_DER_V1,'OFF_CONVAL'!E6)=0),1,0) | F6: =IF(AND('OFF_CONVAL'!F6<>"",LEN('OFF_CONVAL'!F6)>20),1,0) | G6: =IF(AND('OFF_CONVAL'!G6<>"",IF(ISNUMBER('OFF_CONVAL'!G6),OR('OFF_CONVAL'!G6<>INT('OFF_CONVAL'!G6),LEN(TEXT(ABS('OFF_CONVAL'!G6),"0"))>3),TRUE)),1,0) | H6: =IF(AND('OFF_CONVAL'!H6<>"",IF(ISNUMBER('OFF_CONVAL'!H6),OR('OFF_CONVAL'!H6<>INT('OFF_CONVAL'!H6),LEN(TEXT(ABS('OFF_CONVAL'!H6),"0"))>15),TRUE)),1,0) | I6: =IF(AND('OFF_CONVAL'!I6<>"",OR(LEN('OFF_CONVAL'!I6)>3,COUNTIF(CL_MONEDAISO,'OFF_CONVAL'!I6)=0)),1,0) | J6: =IF(AND('OFF_CONVAL'!J6<>"",IF(ISNUMBER('OFF_CONVAL'!J6),OR('OFF_CONVAL'!J6<>INT('OFF_CONVAL'!J6),LEN(TEXT(ABS('OFF_CONVAL'!J6),"0"))>15),TRUE)),1,0) | K6: =IF(AND('OFF_CONVAL'!K6<>"",OR(LEN('OFF_CONVAL'!K6)>3,COUNTIF(CL_MONEDAISO,'OFF_CONVAL'!K6)=0)),1,0) | L6: =IF(AND('OFF_CONVAL'!L6<>"",IF(ISNUMBER('OFF_CONVAL'!L6),OR('OFF_CONVAL'!L6<>INT('OFF_CONVAL'!L6),LEN(TEXT(ABS('OFF_CONVAL'!L6),"0"))>5),TRUE)),1,0) | M6: =IF(AND('OFF_CONVAL'!M6<>"",IF(ISNUMBER('OFF_CONVAL'!M6),OR('OFF_CONVAL'!M6<>INT('OFF_CONVAL'!M6),LEN(TEXT(ABS('OFF_CONVAL'!M6),"0"))>5),TRUE)),1,0) | N6: =IF(AND('OFF_CONVAL'!N6<>"",LEN('OFF_CONVAL'!N6)>20),1,0) | O6: =IF(AND('OFF_CONVAL'!O6<>"",IF(ISNUMBER('OFF_CONVAL'!O6),OR('OFF_CONVAL'!O6<>INT('OFF_CONVAL'!O6),LEN(TEXT(ABS('OFF_CONVAL'!O6),"0"))>15),TRUE)),1,0) | P6: =IF(AND('OFF_CONVAL'!P6<>"",OR(LEN('OFF_CONVAL'!P6)>3,COUNTIF(CL_MONEDAISO,'OFF_CONVAL'!P6)=0)),1,0) | Q6: =IF(AND('OFF_CONVAL'!Q6<>"",NOT(ISNUMBER('OFF_CONVAL'!Q6))),1,0)
A7: =IF(AND('OFF_CONVAL'!A7<>"",NOT(ISNUMBER('OFF_CONVAL'!A7))),1,0) | B7: =IF(AND('OFF_CONVAL'!B7<>"",LEN('OFF_CONVAL'!B7)>20),1,0) | C7: =IF(AND('OFF_CONVAL'!C7<>"",OR(LEN('OFF_CONVAL'!C7)>1,COUNTIF(CL_POSICIONOPERACION_V4,'OFF_CONVAL'!C7)=0)),1,0) | D7: =IF(AND('OFF_CONVAL'!D7<>"",OR(LEN('OFF_CONVAL'!D7)>2,COUNTIF(CL_OBJ_OPE_V1,'OFF_CONVAL'!D7)=0)),1,0) | E7: =IF(AND('OFF_CONVAL'!E7<>"",COUNTIF(CL_PAQ_EST_DER_V1,'OFF_CONVAL'!E7)=0),1,0) | F7: =IF(AND('OFF_CONVAL'!F7<>"",LEN('OFF_CONVAL'!F7)>20),1,0) | G7: =IF(AND('OFF_CONVAL'!G7<>"",IF(ISNUMBER('OFF_CONVAL'!G7),OR('OFF_CONVAL'!G7<>INT('OFF_CONVAL'!G7),LEN(TEXT(ABS('OFF_CONVAL'!G7),"0"))>3),TRUE)),1,0) | H7: =IF(AND('OFF_CONVAL'!H7<>"",IF(ISNUMBER('OFF_CONVAL'!H7),OR('OFF_CONVAL'!H7<>INT('OFF_CONVAL'!H7),LEN(TEXT(ABS('OFF_CONVAL'!H7),"0"))>15),TRUE)),1,0) | I7: =IF(AND('OFF_CONVAL'!I7<>"",OR(LEN('OFF_CONVAL'!I7)>3,COUNTIF(CL_MONEDAISO,'OFF_CONVAL'!I7)=0)),1,0) | J7: =IF(AND('OFF_CONVAL'!J7<>"",IF(ISNUMBER('OFF_CONVAL'!J7),OR('OFF_CONVAL'!J7<>INT('OFF_CONVAL'!J7),LEN(TEXT(ABS('OFF_CONVAL'!J7),"0"))>15),TRUE)),1,0) | K7: =IF(AND('OFF_CONVAL'!K7<>"",OR(LEN('OFF_CONVAL'!K7)>3,COUNTIF(CL_MONEDAISO,'OFF_CONVAL'!K7)=0)),1,0) | L7: =IF(AND('OFF_CONVAL'!L7<>"",IF(ISNUMBER('OFF_CONVAL'!L7),OR('OFF_CONVAL'!L7<>INT('OFF_CONVAL'!L7),LEN(TEXT(ABS('OFF_CONVAL'!L7),"0"))>5),TRUE)),1,0) | M7: =IF(AND('OFF_CONVAL'!M7<>"",IF(ISNUMBER('OFF_CONVAL'!M7),OR('OFF_CONVAL'!M7<>INT('OFF_CONVAL'!M7),LEN(TEXT(ABS('OFF_CONVAL'!M7),"0"))>5),TRUE)),1,0) | N7: =IF(AND('OFF_CONVAL'!N7<>"",LEN('OFF_CONVAL'!N7)>20),1,0) | O7: =IF(AND('OFF_CONVAL'!O7<>"",IF(ISNUMBER('OFF_CONVAL'!O7),OR('OFF_CONVAL'!O7<>INT('OFF_CONVAL'!O7),LEN(TEXT(ABS('OFF_CONVAL'!O7),"0"))>15),TRUE)),1,0) | P7: =IF(AND('OFF_CONVAL'!P7<>"",OR(LEN('OFF_CONVAL'!P7)>3,COUNTIF(CL_MONEDAISO,'OFF_CONVAL'!P7)=0)),1,0) | Q7: =IF(AND('OFF_CONVAL'!Q7<>"",NOT(ISNUMBER('OFF_CONVAL'!Q7))),1,0)
A8: =IF(AND('OFF_CONVAL'!A8<>"",NOT(ISNUMBER('OFF_CONVAL'!A8))),1,0) | B8: =IF(AND('OFF_CONVAL'!B8<>"",LEN('OFF_CONVAL'!B8)>20),1,0) | C8: =IF(AND('OFF_CONVAL'!C8<>"",OR(LEN('OFF_CONVAL'!C8)>1,COUNTIF(CL_POSICIONOPERACION_V4,'OFF_CONVAL'!C8)=0)),1,0) | D8: =IF(AND('OFF_CONVAL'!D8<>"",OR(LEN('OFF_CONVAL'!D8)>2,COUNTIF(CL_OBJ_OPE_V1,'OFF_CONVAL'!D8)=0)),1,0) | E8: =IF(AND('OFF_CONVAL'!E8<>"",COUNTIF(CL_PAQ_EST_DER_V1,'OFF_CONVAL'!E8)=0),1,0) | F8: =IF(AND('OFF_CONVAL'!F8<>"",LEN('OFF_CONVAL'!F8)>20),1,0) | G8: =IF(AND('OFF_CONVAL'!G8<>"",IF(ISNUMBER('OFF_CONVAL'!G8),OR('OFF_CONVAL'!G8<>INT('OFF_CONVAL'!G8),LEN(TEXT(ABS('OFF_CONVAL'!G8),"0"))>3),TRUE)),1,0) | H8: =IF(AND('OFF_CONVAL'!H8<>"",IF(ISNUMBER('OFF_CONVAL'!H8),OR('OFF_CONVAL'!H8<>INT('OFF_CONVAL'!H8),LEN(TEXT(ABS('OFF_CONVAL'!H8),"0"))>15),TRUE)),1,0) | I8: =IF(AND('OFF_CONVAL'!I8<>"",OR(LEN('OFF_CONVAL'!I8)>3,COUNTIF(CL_MONEDAISO,'OFF_CONVAL'!I8)=0)),1,0) | J8: =IF(AND('OFF_CONVAL'!J8<>"",IF(ISNUMBER('OFF_CONVAL'!J8),OR('OFF_CONVAL'!J8<>INT('OFF_CONVAL'!J8),LEN(TEXT(ABS('OFF_CONVAL'!J8),"0"))>15),TRUE)),1,0) | K8: =IF(AND('OFF_CONVAL'!K8<>"",OR(LEN('OFF_CONVAL'!K8)>3,COUNTIF(CL_MONEDAISO,'OFF_CONVAL'!K8)=0)),1,0) | L8: =IF(AND('OFF_CONVAL'!L8<>"",IF(ISNUMBER('OFF_CONVAL'!L8),OR('OFF_CONVAL'!L8<>INT('OFF_CONVAL'!L8),LEN(TEXT(ABS('OFF_CONVAL'!L8),"0"))>5),TRUE)),1,0) | M8: =IF(AND('OFF_CONVAL'!M8<>"",IF(ISNUMBER('OFF_CONVAL'!M8),OR('OFF_CONVAL'!M8<>INT('OFF_CONVAL'!M8),LEN(TEXT(ABS('OFF_CONVAL'!M8),"0"))>5),TRUE)),1,0) | N8: =IF(AND('OFF_CONVAL'!N8<>"",LEN('OFF_CONVAL'!N8)>20),1,0) | O8: =IF(AND('OFF_CONVAL'!O8<>"",IF(ISNUMBER('OFF_CONVAL'!O8),OR('OFF_CONVAL'!O8<>INT('OFF_CONVAL'!O8),LEN(TEXT(ABS('OFF_CONVAL'!O8),"0"))>15),TRUE)),1,0) | P8: =IF(AND('OFF_CONVAL'!P8<>"",OR(LEN('OFF_CONVAL'!P8)>3,COUNTIF(CL_MONEDAISO,'OFF_CONVAL'!P8)=0)),1,0) | Q8: =IF(AND('OFF_CONVAL'!Q8<>"",NOT(ISNUMBER('OFF_CONVAL'!Q8))),1,0)
A9: =IF(AND('OFF_CONVAL'!A9<>"",NOT(ISNUMBER('OFF_CONVAL'!A9))),1,0) | B9: =IF(AND('OFF_CONVAL'!B9<>"",LEN('OFF_CONVAL'!B9)>20),1,0) | C9: =IF(AND('OFF_CONVAL'!C9<>"",OR(LEN('OFF_CONVAL'!C9)>1,COUNTIF(CL_POSICIONOPERACION_V4,'OFF_CONVAL'!C9)=0)),1,0) | D9: =IF(AND('OFF_CONVAL'!D9<>"",OR(LEN('OFF_CONVAL'!D9)>2,COUNTIF(CL_OBJ_OPE_V1,'OFF_CONVAL'!D9)=0)),1,0) | E9: =IF(AND('OFF_CONVAL'!E9<>"",COUNTIF(CL_PAQ_EST_DER_V1,'OFF_CONVAL'!E9)=0),1,0) | F9: =IF(AND('OFF_CONVAL'!F9<>"",LEN('OFF_CONVAL'!F9)>20),1,0) | G9: =IF(AND('OFF_CONVAL'!G9<>"",IF(ISNUMBER('OFF_CONVAL'!G9),OR('OFF_CONVAL'!G9<>INT('OFF_CONVAL'!G9),LEN(TEXT(ABS('OFF_CONVAL'!G9),"0"))>3),TRUE)),1,0) | H9: =IF(AND('OFF_CONVAL'!H9<>"",IF(ISNUMBER('OFF_CONVAL'!H9),OR('OFF_CONVAL'!H9<>INT('OFF_CONVAL'!H9),LEN(TEXT(ABS('OFF_CONVAL'!H9),"0"))>15),TRUE)),1,0) | I9: =IF(AND('OFF_CONVAL'!I9<>"",OR(LEN('OFF_CONVAL'!I9)>3,COUNTIF(CL_MONEDAISO,'OFF_CONVAL'!I9)=0)),1,0) | J9: =IF(AND('OFF_CONVAL'!J9<>"",IF(ISNUMBER('OFF_CONVAL'!J9),OR('OFF_CONVAL'!J9<>INT('OFF_CONVAL'!J9),LEN(TEXT(ABS('OFF_CONVAL'!J9),"0"))>15),TRUE)),1,0) | K9: =IF(AND('OFF_CONVAL'!K9<>"",OR(LEN('OFF_CONVAL'!K9)>3,COUNTIF(CL_MONEDAISO,'OFF_CONVAL'!K9)=0)),1,0) | L9: =IF(AND('OFF_CONVAL'!L9<>"",IF(ISNUMBER('OFF_CONVAL'!L9),OR('OFF_CONVAL'!L9<>INT('OFF_CONVAL'!L9),LEN(TEXT(ABS('OFF_CONVAL'!L9),"0"))>5),TRUE)),1,0) | M9: =IF(AND('OFF_CONVAL'!M9<>"",IF(ISNUMBER('OFF_CONVAL'!M9),OR('OFF_CONVAL'!M9<>INT('OFF_CONVAL'!M9),LEN(TEXT(ABS('OFF_CONVAL'!M9),"0"))>5),TRUE)),1,0) | N9: =IF(AND('OFF_CONVAL'!N9<>"",LEN('OFF_CONVAL'!N9)>20),1,0) | O9: =IF(AND('OFF_CONVAL'!O9<>"",IF(ISNUMBER('OFF_CONVAL'!O9),OR('OFF_CONVAL'!O9<>INT('OFF_CONVAL'!O9),LEN(TEXT(ABS('OFF_CONVAL'!O9),"0"))>15),TRUE)),1,0) | P9: =IF(AND('OFF_CONVAL'!P9<>"",OR(LEN('OFF_CONVAL'!P9)>3,COUNTIF(CL_MONEDAISO,'OFF_CONVAL'!P9)=0)),1,0) | Q9: =IF(AND('OFF_CONVAL'!Q9<>"",NOT(ISNUMBER('OFF_CONVAL'!Q9))),1,0)
A10: =IF(AND('OFF_CONVAL'!A10<>"",NOT(ISNUMBER('OFF_CONVAL'!A10))),1,0) | B10: =IF(AND('OFF_CONVAL'!B10<>"",LEN('OFF_CONVAL'!B10)>20),1,0) | C10: =IF(AND('OFF_CONVAL'!C10<>"",OR(LEN('OFF_CONVAL'!C10)>1,COUNTIF(CL_POSICIONOPERACION_V4,'OFF_CONVAL'!C10)=0)),1,0) | D10: =IF(AND('OFF_CONVAL'!D10<>"",OR(LEN('OFF_CONVAL'!D10)>2,COUNTIF(CL_OBJ_OPE_V1,'OFF_CONVAL'!D10)=0)),1,0) | E10: =IF(AND('OFF_CONVAL'!E10<>"",COUNTIF(CL_PAQ_EST_DER_V1,'OFF_CONVAL'!E10)=0),1,0) | F10: =IF(AND('OFF_CONVAL'!F10<>"",LEN('OFF_CONVAL'!F10)>20),1,0) | G10: =IF(AND('OFF_CONVAL'!G10<>"",IF(ISNUMBER('OFF_CONVAL'!G10),OR('OFF_CONVAL'!G10<>INT('OFF_CONVAL'!G10),LEN(TEXT(ABS('OFF_CONVAL'!G10),"0"))>3),TRUE)),1,0) | H10: =IF(AND('OFF_CONVAL'!H10<>"",IF(ISNUMBER('OFF_CONVAL'!H10),OR('OFF_CONVAL'!H10<>INT('OFF_CONVAL'!H10),LEN(TEXT(ABS('OFF_CONVAL'!H10),"0"))>15),TRUE)),1,0) | I10: =IF(AND('OFF_CONVAL'!I10<>"",OR(LEN('OFF_CONVAL'!I10)>3,COUNTIF(CL_MONEDAISO,'OFF_CONVAL'!I10)=0)),1,0) | J10: =IF(AND('OFF_CONVAL'!J10<>"",IF(ISNUMBER('OFF_CONVAL'!J10),OR('OFF_CONVAL'!J10<>INT('OFF_CONVAL'!J10),LEN(TEXT(ABS('OFF_CONVAL'!J10),"0"))>15),TRUE)),1,0) | K10: =IF(AND('OFF_CONVAL'!K10<>"",OR(LEN('OFF_CONVAL'!K10)>3,COUNTIF(CL_MONEDAISO,'OFF_CONVAL'!K10)=0)),1,0) | L10: =IF(AND('OFF_CONVAL'!L10<>"",IF(ISNUMBER('OFF_CONVAL'!L10),OR('OFF_CONVAL'!L10<>INT('OFF_CONVAL'!L10),LEN(TEXT(ABS('OFF_CONVAL'!L10),"0"))>5),TRUE)),1,0) | M10: =IF(AND('OFF_CONVAL'!M10<>"",IF(ISNUMBER('OFF_CONVAL'!M10),OR('OFF_CONVAL'!M10<>INT('OFF_CONVAL'!M10),LEN(TEXT(ABS('OFF_CONVAL'!M10),"0"))>5),TRUE)),1,0) | N10: =IF(AND('OFF_CONVAL'!N10<>"",LEN('OFF_CONVAL'!N10)>20),1,0) | O10: =IF(AND('OFF_CONVAL'!O10<>"",IF(ISNUMBER('OFF_CONVAL'!O10),OR('OFF_CONVAL'!O10<>INT('OFF_CONVAL'!O10),LEN(TEXT(ABS('OFF_CONVAL'!O10),"0"))>15),TRUE)),1,0) | P10: =IF(AND('OFF_CONVAL'!P10<>"",OR(LEN('OFF_CONVAL'!P10)>3,COUNTIF(CL_MONEDAISO,'OFF_CONVAL'!P10)=0)),1,0) | Q10: =IF(AND('OFF_CONVAL'!Q10<>"",NOT(ISNUMBER('OFF_CONVAL'!Q10))),1,0)
A11: =IF(AND('OFF_CONVAL'!A11<>"",NOT(ISNUMBER('OFF_CONVAL'!A11))),1,0) | B11: =IF(AND('OFF_CONVAL'!B11<>"",LEN('OFF_CONVAL'!B11)>20),1,0) | C11: =IF(AND('OFF_CONVAL'!C11<>"",OR(LEN('OFF_CONVAL'!C11)>1,COUNTIF(CL_POSICIONOPERACION_V4,'OFF_CONVAL'!C11)=0)),1,0) | D11: =IF(AND('OFF_CONVAL'!D11<>"",OR(LEN('OFF_CONVAL'!D11)>2,COUNTIF(CL_OBJ_OPE_V1,'OFF_CONVAL'!D11)=0)),1,0) | E11: =IF(AND('OFF_CONVAL'!E11<>"",COUNTIF(CL_PAQ_EST_DER_V1,'OFF_CONVAL'!E11)=0),1,0) | F11: =IF(AND('OFF_CONVAL'!F11<>"",LEN('OFF_CONVAL'!F11)>20),1,0) | G11: =IF(AND('OFF_CONVAL'!G11<>"",IF(ISNUMBER('OFF_CONVAL'!G11),OR('OFF_CONVAL'!G11<>INT('OFF_CONVAL'!G11),LEN(TEXT(ABS('OFF_CONVAL'!G11),"0"))>3),TRUE)),1,0) | H11: =IF(AND('OFF_CONVAL'!H11<>"",IF(ISNUMBER('OFF_CONVAL'!H11),OR('OFF_CONVAL'!H11<>INT('OFF_CONVAL'!H11),LEN(TEXT(ABS('OFF_CONVAL'!H11),"0"))>15),TRUE)),1,0) | I11: =IF(AND('OFF_CONVAL'!I11<>"",OR(LEN('OFF_CONVAL'!I11)>3,COUNTIF(CL_MONEDAISO,'OFF_CONVAL'!I11)=0)),1,0) | J11: =IF(AND('OFF_CONVAL'!J11<>"",IF(ISNUMBER('OFF_CONVAL'!J11),OR('OFF_CONVAL'!J11<>INT('OFF_CONVAL'!J11),LEN(TEXT(ABS('OFF_CONVAL'!J11),"0"))>15),TRUE)),1,0) | K11: =IF(AND('OFF_CONVAL'!K11<>"",OR(LEN('OFF_CONVAL'!K11)>3,COUNTIF(CL_MONEDAISO,'OFF_CONVAL'!K11)=0)),1,0) | L11: =IF(AND('OFF_CONVAL'!L11<>"",IF(ISNUMBER('OFF_CONVAL'!L11),OR('OFF_CONVAL'!L11<>INT('OFF_CONVAL'!L11),LEN(TEXT(ABS('OFF_CONVAL'!L11),"0"))>5),TRUE)),1,0) | M11: =IF(AND('OFF_CONVAL'!M11<>"",IF(ISNUMBER('OFF_CONVAL'!M11),OR('OFF_CONVAL'!M11<>INT('OFF_CONVAL'!M11),LEN(TEXT(ABS('OFF_CONVAL'!M11),"0"))>5),TRUE)),1,0) | N11: =IF(AND('OFF_CONVAL'!N11<>"",LEN('OFF_CONVAL'!N11)>20),1,0) | O11: =IF(AND('OFF_CONVAL'!O11<>"",IF(ISNUMBER('OFF_CONVAL'!O11),OR('OFF_CONVAL'!O11<>INT('OFF_CONVAL'!O11),LEN(TEXT(ABS('OFF_CONVAL'!O11),"0"))>15),TRUE)),1,0) | P11: =IF(AND('OFF_CONVAL'!P11<>"",OR(LEN('OFF_CONVAL'!P11)>3,COUNTIF(CL_MONEDAISO,'OFF_CONVAL'!P11)=0)),1,0) | Q11: =IF(AND('OFF_CONVAL'!Q11<>"",NOT(ISNUMBER('OFF_CONVAL'!Q11))),1,0)
A12: =IF(AND('OFF_CONVAL'!A12<>"",NOT(ISNUMBER('OFF_CONVAL'!A12))),1,0) | B12: =IF(AND('OFF_CONVAL'!B12<>"",LEN('OFF_CONVAL'!B12)>20),1,0) | C12: =IF(AND('OFF_CONVAL'!C12<>"",OR(LEN('OFF_CONVAL'!C12)>1,COUNTIF(CL_POSICIONOPERACION_V4,'OFF_CONVAL'!C12)=0)),1,0) | D12: =IF(AND('OFF_CONVAL'!D12<>"",OR(LEN('OFF_CONVAL'!D12)>2,COUNTIF(CL_OBJ_OPE_V1,'OFF_CONVAL'!D12)=0)),1,0) | E12: =IF(AND('OFF_CONVAL'!E12<>"",COUNTIF(CL_PAQ_EST_DER_V1,'OFF_CONVAL'!E12)=0),1,0) | F12: =IF(AND('OFF_CONVAL'!F12<>"",LEN('OFF_CONVAL'!F12)>20),1,0) | G12: =IF(AND('OFF_CONVAL'!G12<>"",IF(ISNUMBER('OFF_CONVAL'!G12),OR('OFF_CONVAL'!G12<>INT('OFF_CONVAL'!G12),LEN(TEXT(ABS('OFF_CONVAL'!G12),"0"))>3),TRUE)),1,0) | H12: =IF(AND('OFF_CONVAL'!H12<>"",IF(ISNUMBER('OFF_CONVAL'!H12),OR('OFF_CONVAL'!H12<>INT('OFF_CONVAL'!H12),LEN(TEXT(ABS('OFF_CONVAL'!H12),"0"))>15),TRUE)),1,0) | I12: =IF(AND('OFF_CONVAL'!I12<>"",OR(LEN('OFF_CONVAL'!I12)>3,COUNTIF(CL_MONEDAISO,'OFF_CONVAL'!I12)=0)),1,0) | J12: =IF(AND('OFF_CONVAL'!J12<>"",IF(ISNUMBER('OFF_CONVAL'!J12),OR('OFF_CONVAL'!J12<>INT('OFF_CONVAL'!J12),LEN(TEXT(ABS('OFF_CONVAL'!J12),"0"))>15),TRUE)),1,0) | K12: =IF(AND('OFF_CONVAL'!K12<>"",OR(LEN('OFF_CONVAL'!K12)>3,COUNTIF(CL_MONEDAISO,'OFF_CONVAL'!K12)=0)),1,0) | L12: =IF(AND('OFF_CONVAL'!L12<>"",IF(ISNUMBER('OFF_CONVAL'!L12),OR('OFF_CONVAL'!L12<>INT('OFF_CONVAL'!L12),LEN(TEXT(ABS('OFF_CONVAL'!L12),"0"))>5),TRUE)),1,0) | M12: =IF(AND('OFF_CONVAL'!M12<>"",IF(ISNUMBER('OFF_CONVAL'!M12),OR('OFF_CONVAL'!M12<>INT('OFF_CONVAL'!M12),LEN(TEXT(ABS('OFF_CONVAL'!M12),"0"))>5),TRUE)),1,0) | N12: =IF(AND('OFF_CONVAL'!N12<>"",LEN('OFF_CONVAL'!N12)>20),1,0) | O12: =IF(AND('OFF_CONVAL'!O12<>"",IF(ISNUMBER('OFF_CONVAL'!O12),OR('OFF_CONVAL'!O12<>INT('OFF_CONVAL'!O12),LEN(TEXT(ABS('OFF_CONVAL'!O12),"0"))>15),TRUE)),1,0) | P12: =IF(AND('OFF_CONVAL'!P12<>"",OR(LEN('OFF_CONVAL'!P12)>3,COUNTIF(CL_MONEDAISO,'OFF_CONVAL'!P12)=0)),1,0) | Q12: =IF(AND('OFF_CONVAL'!Q12<>"",NOT(ISNUMBER('OFF_CONVAL'!Q12))),1,0)
A13: =IF(AND('OFF_CONVAL'!A13<>"",NOT(ISNUMBER('OFF_CONVAL'!A13))),1,0) | B13: =IF(AND('OFF_CONVAL'!B13<>"",LEN('OFF_CONVAL'!B13)>20),1,0) | C13: =IF(AND('OFF_CONVAL'!C13<>"",OR(LEN('OFF_CONVAL'!C13)>1,COUNTIF(CL_POSICIONOPERACION_V4,'OFF_CONVAL'!C13)=0)),1,0) | D13: =IF(AND('OFF_CONVAL'!D13<>"",OR(LEN('OFF_CONVAL'!D13)>2,COUNTIF(CL_OBJ_OPE_V1,'OFF_CONVAL'!D13)=0)),1,0) | E13: =IF(AND('OFF_CONVAL'!E13<>"",COUNTIF(CL_PAQ_EST_DER_V1,'OFF_CONVAL'!E13)=0),1,0) | F13: =IF(AND('OFF_CONVAL'!F13<>"",LEN('OFF_CONVAL'!F13)>20),1,0) | G13: =IF(AND('OFF_CONVAL'!G13<>"",IF(ISNUMBER('OFF_CONVAL'!G13),OR('OFF_CONVAL'!G13<>INT('OFF_CONVAL'!G13),LEN(TEXT(ABS('OFF_CONVAL'!G13),"0"))>3),TRUE)),1,0) | H13: =IF(AND('OFF_CONVAL'!H13<>"",IF(ISNUMBER('OFF_CONVAL'!H13),OR('OFF_CONVAL'!H13<>INT('OFF_CONVAL'!H13),LEN(TEXT(ABS('OFF_CONVAL'!H13),"0"))>15),TRUE)),1,0) | I13: =IF(AND('OFF_CONVAL'!I13<>"",OR(LEN('OFF_CONVAL'!I13)>3,COUNTIF(CL_MONEDAISO,'OFF_CONVAL'!I13)=0)),1,0) | J13: =IF(AND('OFF_CONVAL'!J13<>"",IF(ISNUMBER('OFF_CONVAL'!J13),OR('OFF_CONVAL'!J13<>INT('OFF_CONVAL'!J13),LEN(TEXT(ABS('OFF_CONVAL'!J13),"0"))>15),TRUE)),1,0) | K13: =IF(AND('OFF_CONVAL'!K13<>"",OR(LEN('OFF_CONVAL'!K13)>3,COUNTIF(CL_MONEDAISO,'OFF_CONVAL'!K13)=0)),1,0) | L13: =IF(AND('OFF_CONVAL'!L13<>"",IF(ISNUMBER('OFF_CONVAL'!L13),OR('OFF_CONVAL'!L13<>INT('OFF_CONVAL'!L13),LEN(TEXT(ABS('OFF_CONVAL'!L13),"0"))>5),TRUE)),1,0) | M13: =IF(AND('OFF_CONVAL'!M13<>"",IF(ISNUMBER('OFF_CONVAL'!M13),OR('OFF_CONVAL'!M13<>INT('OFF_CONVAL'!M13),LEN(TEXT(ABS('OFF_CONVAL'!M13),"0"))>5),TRUE)),1,0) | N13: =IF(AND('OFF_CONVAL'!N13<>"",LEN('OFF_CONVAL'!N13)>20),1,0) | O13: =IF(AND('OFF_CONVAL'!O13<>"",IF(ISNUMBER('OFF_CONVAL'!O13),OR('OFF_CONVAL'!O13<>INT('OFF_CONVAL'!O13),LEN(TEXT(ABS('OFF_CONVAL'!O13),"0"))>15),TRUE)),1,0) | P13: =IF(AND('OFF_CONVAL'!P13<>"",OR(LEN('OFF_CONVAL'!P13)>3,COUNTIF(CL_MONEDAISO,'OFF_CONVAL'!P13)=0)),1,0) | Q13: =IF(AND('OFF_CONVAL'!Q13<>"",NOT(ISNUMBER('OFF_CONVAL'!Q13))),1,0)
... A201: =IF(AND('OFF_CONVAL'!A201<>"",NOT(ISNUMBER('OFF_CONVAL'!A201))),1,0) | B201: =IF(AND('OFF_CONVAL'!B201<>"",LEN('OFF_CONVAL'!B201)>20),1,0) | C201: =IF(AND('OFF_CONVAL'!C201<>"",OR(LEN('OFF_CONVAL'!C201)>1,COUNTIF(CL_POSICIONOPERACION_V4,'OFF_CONVAL'!C201)=0)),1,0) | D201: =IF(AND('OFF_CONVAL'!D201<>"",OR(LEN('OFF_CONVAL'!D201)>2,COUNTIF(CL_OBJ_OPE_V1,'OFF_CONVAL'!D201)=0)),1,0) | E201: =IF(AND('OFF_CONVAL'!E201<>"",COUNTIF(CL_PAQ_EST_DER_V1,'OFF_CONVAL'!E201)=0),1,0) | F201: =IF(AND('OFF_CONVAL'!F201<>"",LEN('OFF_CONVAL'!F201)>20),1,0) | G201: =IF(AND('OFF_CONVAL'!G201<>"",IF(ISNUMBER('OFF_CONVAL'!G201),OR('OFF_CONVAL'!G201<>INT('OFF_CONVAL'!G201),LEN(TEXT(ABS('OFF_CONVAL'!G201),"0"))>3),TRUE)),1,0) | H201: =IF(AND('OFF_CONVAL'!H201<>"",IF(ISNUMBER('OFF_CONVAL'!H201),OR('OFF_CONVAL'!H201<>INT('OFF_CONVAL'!H201),LEN(TEXT(ABS('OFF_CONVAL'!H201),"0"))>15),TRUE)),1,0) | I201: =IF(AND('OFF_CONVAL'!I201<>"",OR(LEN('OFF_CONVAL'!I201)>3,COUNTIF(CL_MONEDAISO,'OFF_CONVAL'!I201)=0)),1,0) | J201: =IF(AND('OFF_CONVAL'!J201<>"",IF(ISNUMBER('OFF_CONVAL'!J201),OR('OFF_CONVAL'!J201<>INT('OFF_CONVAL'!J201),LEN(TEXT(ABS('OFF_CONVAL'!J201),"0"))>15),TRUE)),1,0) | K201: =IF(AND('OFF_CONVAL'!K201<>"",OR(LEN('OFF_CONVAL'!K201)>3,COUNTIF(CL_MONEDAISO,'OFF_CONVAL'!K201)=0)),1,0) | L201: =IF(AND('OFF_CONVAL'!L201<>"",IF(ISNUMBER('OFF_CONVAL'!L201),OR('OFF_CONVAL'!L201<>INT('OFF_CONVAL'!L201),LEN(TEXT(ABS('OFF_CONVAL'!L201),"0"))>5),TRUE)),1,0) | M201: =IF(AND('OFF_CONVAL'!M201<>"",IF(ISNUMBER('OFF_CONVAL'!M201),OR('OFF_CONVAL'!M201<>INT('OFF_CONVAL'!M201),LEN(TEXT(ABS('OFF_CONVAL'!M201),"0"))>5),TRUE)),1,0) | N201: =IF(AND('OFF_CONVAL'!N201<>"",LEN('OFF_CONVAL'!N201)>20),1,0) | O201: =IF(AND('OFF_CONVAL'!O201<>"",IF(ISNUMBER('OFF_CONVAL'!O201),OR('OFF_CONVAL'!O201<>INT('OFF_CONVAL'!O201),LEN(TEXT(ABS('OFF_CONVAL'!O201),"0"))>15),TRUE)),1,0) | P201: =IF(AND('OFF_CONVAL'!P201<>"",OR(LEN('OFF_CONVAL'!P201)>3,COUNTIF(CL_MONEDAISO,'OFF_CONVAL'!P201)=0)),1,0) | Q201: =IF(AND('OFF_CONVAL'!Q201<>"",NOT(ISNUMBER('OFF_CONVAL'!Q201))),1,0)
