Workbook
Name CL_TIPO_OPERACION_CF_I: CAT_TIPO_OPERACION_CF_I!$A$2:$A$5
Name CL_TIPO_FONDEO_CF_I: CAT_TIPO_FONDEO_CF_I!$A$2:$A$10
Name CL_MONEDA_ISO: CAT_MONEDA_ISO!$A$2:$A$190
Name CL_TIPO_RELACION_ACREDITADO: CAT_TIPO_RELACION_ACREDITADO!$A$2:$A$10

Sheet VALIDACION
A1: RESUMEN DE VALIDACIÓN
A2: Total celdas con error de formato: | C2: =SUM(CHK!A2:I201)
A3: Estado: | C3: =IF(C2=0,"✔ SIN ERRORES DE FORMATO","✖ REVISAR: "&C2&" celda(s) marcada(s) en rojo")
A5: Orden | B5: Campo | C5: Tipo | D5: Long | E5: Catálogo | F5: # Errores | G5: # Vacíos (obligatorio)
A6: 1 | B6: TIPOOPERACION | C6: NUMERICO | D6: 2 | E6: TIPO OPERACION CF I | F6: =SUM(CHK!A2:A201) | G6: =COUNTBLANK('CF_I'!A2:A201)
A7: 2 | B7: TIPOFONDEO | C7: NUMERICO | D7: 2 | E7: TIPO FONDEO CF I | F7: =SUM(CHK!B2:B201) | G7: =COUNTBLANK('CF_I'!B2:B201)
A8: 3 | B8: FECHA_INICIO | C8: FECHA | D8: DD/MM/AAAA | E8: — | F8: =SUM(CHK!C2:C201) | G8: =COUNTBLANK('CF_I'!C2:C201)
A9: 4 | B9: FECHA_VENC | C9: FECHA | D9: DD/MM/AAAA | E9: — | F9: =SUM(CHK!D2:D201) | G9: =COUNTBLANK('CF_I'!D2:D201)
A10: 5 | B10: MONTO_OPER | C10: NUMERICO | D10: 12 | E10: — | F10: =SUM(CHK!E2:E201) | G10: =COUNTBLANK('CF_I'!E2:E201)
A11: 6 | B11: MONEDA | C11: TEXTO | D11: 3 | E11: MONEDA ISO | F11: =SUM(CHK!F2:F201) | G11: =COUNTBLANK('CF_I'!F2:F201)
A12: 7 | B12: CVE_ACREEDOR | C12: TEXTO | D12: 6 | E12: — | F12: =SUM(CHK!G2:G201) | G12: =COUNTBLANK('CF_I'!G2:G201)
A13: 8 | B13: CVE_OPERACION | C13: TEXTO | D13: 34 | E13: — | F13: =SUM(CHK!H2:H201) | G13: =COUNTBLANK('CF_I'!H2:H201)
A14: 9 | B14: TIP_REL_ACREED | C14: NUMERICO | D14: 2 | E14: TIPO RELACION ACREDITADO | F14: =SUM(CHK!I2:I201) | G14: =COUNTBLANK('CF_I'!I2:I201)

Sheet CF_I
A1: TIPOOPERACION | B1: TIPOFONDEO | C1: FECHA_INICIO | D1: FECHA_VENC | E1: MONTO_OPER | F1: MONEDA | G1: CVE_ACREEDOR | H1: CVE_OPERACION | I1: TIP_REL_ACREED

Sheet CAT_TIPO_OPERACION_CF_I
A1: Clave | B1: Descripcion
A2: 1 | B2: Depósitos de Exigibilidad Inmediata sin interés
A3: 2 | B3: Depósitos de Exigibilidad Inmediata con interés
A4: 3 | B4: Depósitos a Plazo del Público en General
A5: 4 | B5: Depósitos a Plazo del Mercado de Dinero

Sheet CAT_TIPO_FONDEO_CF_I
A1: Clave | B1: Descripcion
A2: 1 | B2: Fondeo Minorista, asegurados por el IPAB, con relación transaccional
A3: 2 | B3: Fondeo Minorista, asegurados por el IPAB, sin relación transaccional
A4: 3 | B4: Fondeo Minorista, no asegurados por el IPAB, con relación transaccional
A5: 4 | B5: Fondeo Minorista, no asegurados por el IPAB, sin relación transaccional
A6: 5 | B6: Fondeo Mayorista, con relación operacional, asegurados por el IPAB. Monto que mantiene cada empresa para asegurar el cumplimiento de las operaciones relacionadas con el propósito de la cuenta, o para evitar cobros o cancelaciones (lo que resulte mayor en cada caso)
A7: 6 | B7: Fondeo Mayorista, con relación operacional, asegurados por el IPAB. Monto en exceso a la cantidad anterior
A8: 7 | B8: Fondeo Mayorista, con relación operacional, no asegurados por el IPAB. Monto que mantiene cada empresa para asegurar el cumplimiento de las operaciones relacionadas con el propósito de la cuenta, o para evitar cobros o cancelaciones (lo que resulte mayor en cada caso)
A9: 8 | B9: Fondeo Mayorista, con relación operacional, no asegurados por el IPAB. Monto en exceso a la cantidad anterior
A10: 9 | B10: Fondeo Mayorista, sin relación operacional

Sheet CAT_MONEDA_ISO
A1: Clave | B1: Descripcion
A2: AED | B2: UAE Dirham
A3: AFN | B3: Afghani
A4: ALL | B4: Lek
A5: AMD | B5: Armenian Dram
A6: ANG | B6: Netherlands Antillean Guilder
A7: AOA | B7: Kwanza
A8: ARS | B8: Argentine Peso
A9: AUD | B9: Australian Dollar
A10: AWG | B10: Aruban Guilder
A11: AZN | B11: Azerbaijanian Manat
A12: BAM | B12: Convertible Mark
... A190: ZMW | B190: Kwacha zambiano

Sheet CAT_TIPO_RELACION_ACREDITADO
A1: Clave | B1: Descripcion
A2: 1 | B2: Sin relación
A3: 2 | B3: Poseedoras del 2% o más de los Títulos Representativos
A4: 3 | B4: Miembros del Consejo de Administración
A5: 4 | B5: Cónyuges y personas con parentesco
A6: 5 | B6: Personas con injerencia
A7: 6 | B7: Poseedoras del 10% o más de los títulos representativos
A8: 7 | B8: Consejeros o Administradores
A9: 8 | B9: Personas con poder de mando
A10: 9 | B10: Persona relacionada relevante

Sheet CHK
A2: =IF(AND('CF_I'!A2<>"",COUNTIF(CL_TIPO_OPERACION_CF_I,'CF_I'!A2)=0),1,0) | B2: =IF(AND('CF_I'!B2<>"",COUNTIF(CL_TIPO_FONDEO_CF_I,'CF_I'!B2)=0),1,0) | C2: =IF(AND('CF_I'!C2<>"",NOT(ISNUMBER('CF_I'!C2))),1,0) | D2: =IF(AND('CF_I'!D2<>"",NOT(ISNUMBER('CF_I'!D2))),1,0) | E2: =IF(AND('CF_I'!E2<>"",IF(ISNUMBER('CF_I'!E2),OR('CF_I'!E2<>INT('CF_I'!E2),LEN(TEXT(ABS('CF_I'!E2),"0"))>12),TRUE)),1,0) | F2: =IF(AND('CF_I'!F2<>"",OR(LEN('CF_I'!F2)>3,COUNTIF(CL_MONEDA_ISO,'CF_I'!F2)=0)),1,0) | G2: =IF(AND('CF_I'!G2<>"",LEN('CF_I'!G2)>6),1,0) | H2: =IF(AND('CF_I'!H2<>"",LEN('CF_I'!H2)>34),1,0) | I2: =IF(AND('CF_I'!I2<>"",COUNTIF(CL_TIPO_RELACION_ACREDITADO,'CF_I'!I2)=0),1,0)
A3: =IF(AND('CF_I'!A3<>"",COUNTIF(CL_TIPO_OPERACION_CF_I,'CF_I'!A3)=0),1,0) | B3: =IF(AND('CF_I'!B3<>"",COUNTIF(CL_TIPO_FONDEO_CF_I,'CF_I'!B3)=0),1,0) | C3: =IF(AND('CF_I'!C3<>"",NOT(ISNUMBER('CF_I'!C3))),1,0) | D3: =IF(AND('CF_I'!D3<>"",NOT(ISNUMBER('CF_I'!D3))),1,0) | E3: =IF(AND('CF_I'!E3<>"",IF(ISNUMBER('CF_I'!E3),OR('CF_I'!E3<>INT('CF_I'!E3),LEN(TEXT(ABS('CF_I'!E3),"0"))>12),TRUE)),1,0) | F3: =IF(AND('CF_I'!F3<>"",OR(LEN('CF_I'!F3)>3,COUNTIF(CL_MONEDA_ISO,'CF_I'!F3)=0)),1,0) | G3: =IF(AND('CF_I'!G3<>"",LEN('CF_I'!G3)>6),1,0) | H3: =IF(AND('CF_I'!H3<>"",LEN('CF_I'!H3)>34),1,0) | I3: =IF(AND('CF_I'!I3<>"",COUNTIF(CL_TIPO_RELACION_ACREDITADO,'CF_I'!I3)=0),1,0)
A4: =IF(AND('CF_I'!A4<>"",COUNTIF(CL_TIPO_OPERACION_CF_I,'CF_I'!A4)=0),1,0) | B4: =IF(AND('CF_I'!B4<>"",COUNTIF(CL_TIPO_FONDEO_CF_I,'CF_I'!B4)=0),1,0) | C4: =IF(AND('CF_I'!C4<>"",NOT(ISNUMBER('CF_I'!C4))),1,0) | D4: =IF(AND('CF_I'!D4<>"",NOT(ISNUMBER('CF_I'!D4))),1,0) | E4: =IF(AND('CF_I'!E4<>"",IF(ISNUMBER('CF_I'!E4),OR('CF_I'!E4<>INT('CF_I'!E4),LEN(TEXT(ABS('CF_I'!E4),"0"))>12),TRUE)),1,0) | F4: =IF(AND('CF_I'!F4<>"",OR(LEN('CF_I'!F4)>3,COUNTIF(CL_MONEDA_ISO,'CF_I'!F4)=0)),1,0) | G4: =IF(AND('CF_I'!G4<>"",LEN('CF_I'!G4)>6),1,0) | H4: =IF(AND('CF_I'!H4<>"",LEN('CF_I'!H4)>34),1,0) | I4: =IF(AND('CF_I'!I4<>"",COUNTIF(CL_TIPO_RELACION_ACREDITADO,'CF_I'!I4)=0),1,0)
A5: =IF(AND('CF_I'!A5<>"",COUNTIF(CL_TIPO_OPERACION_CF_I,'CF_I'!A5)=0),1,0) | B5: =IF(AND('CF_I'!B5<>"",COUNTIF(CL_TIPO_FONDEO_CF_I,'CF_I'!B5)=0),1,0) | C5: =IF(AND('CF_I'!C5<>"",NOT(ISNUMBER('CF_I'!C5))),1,0) | D5: =IF(AND('CF_I'!D5<>"",NOT(ISNUMBER('CF_I'!D5))),1,0) | E5: =IF(AND('CF_I'!E5<>"",IF(ISNUMBER('CF_I'!E5),OR('CF_I'!E5<>INT('CF_I'!E5),LEN(TEXT(ABS('CF_I'!E5),"0"))>12),TRUE)),1,0) | F5: =IF(AND('CF_I'!F5<>"",OR(LEN('CF_I'!F5)>3,COUNTIF(CL_MONEDA_ISO,'CF_I'!F5)=0)),1,0) | G5: =IF(AND('CF_I'!G5<>"",LEN('CF_I'!G5)>6),1,0) | H5: =IF(AND('CF_I'!H5<>"",LEN('CF_I'!H5)>34),1,0) | I5: =IF(AND('CF_I'!I5<>"",COUNTIF(CL_TIPO_RELACION_ACREDITADO,'CF_I'!I5)=0),1,0)
A6: =IF(AND('CF_I'!A6<>"",COUNTIF(CL_TIPO_OPERACION_CF_I,'CF_I'!A6)=0),1,0) | B6: =IF(AND('CF_I'!B6<>"",COUNTIF(CL_TIPO_FONDEO_CF_I,'CF_I'!B6)=0),1,0) | C6: =IF(AND('CF_I'!C6<>"",NOT(ISNUMBER('CF_I'!C6))),1,0) | D6: =IF(AND('CF_I'!D6<>"",NOT(ISNUMBER('CF_I'!D6))),1,0) | E6: =IF(AND('CF_I'!E6<>"",IF(ISNUMBER('CF_I'!E6),OR('CF_I'!E6<>INT('CF_I'!E6),LEN(TEXT(ABS('CF_I'!E6),"0"))>12),TRUE)),1,0) | F6: =IF(AND('CF_I'!F6<>"",OR(LEN('CF_I'!F6)>3,COUNTIF(CL_MONEDA_ISO,'CF_I'!F6)=0)),1,0) | G6: =IF(AND('CF_I'!G6<>"",LEN('CF_I'!G6)>6),1,0) | H6: =IF(AND('CF_I'!H6<>"",LEN('CF_I'!H6)>34),1,0) | I6: =IF(AND('CF_I'!I6<>"",COUNTIF(CL_TIPO_RELACION_ACREDITADO,'CF_I'!I6)=0),1,0)
A7: =IF(AND('CF_I'!A7<>"",COUNTIF(CL_TIPO_OPERACION_CF_I,'CF_I'!A7)=0),1,0) | B7: =IF(AND('CF_I'!B7<>"",COUNTIF(CL_TIPO_FONDEO_CF_I,'CF_I'!B7)=0),1,0) | C7: =IF(AND('CF_I'!C7<>"",NOT(ISNUMBER('CF_I'!C7))),1,0) | D7: =IF(AND('CF_I'!D7<>"",NOT(ISNUMBER('CF_I'!D7))),1,0) | E7: =IF(AND('CF_I'!E7<>"",IF(ISNUMBER('CF_I'!E7),OR('CF_I'!E7<>INT('CF_I'!E7),LEN(TEXT(ABS('CF_I'!E7),"0"))>12),TRUE)),1,0) | F7: =IF(AND('CF_I'!F7<>"",OR(LEN('CF_I'!F7)>3,COUNTIF(CL_MONEDA_ISO,'CF_I'!F7)=0)),1,0) | G7: =IF(AND('CF_I'!G7<>"",LEN('CF_I'!G7)>6),1,0) | H7: =IF(AND('CF_I'!H7<>"",LEN('CF_I'!H7)>34),1,0) | I7: =IF(AND('CF_I'!I7<>"",COUNTIF(CL_TIPO_RELACION_ACREDITADO,'CF_I'!I7)=0),1,0)
A8: =IF(AND('CF_I'!A8<>"",COUNTIF(CL_TIPO_OPERACION_CF_I,'CF_I'!A8)=0),1,0) | B8: =IF(AND('CF_I'!B8<>"",COUNTIF(CL_TIPO_FONDEO_CF_I,'CF_I'!B8)=0),1,0) | C8: =IF(AND('CF_I'!C8<>"",NOT(ISNUMBER('CF_I'!C8))),1,0) | D8: =IF(AND('CF_I'!D8<>"",NOT(ISNUMBER('CF_I'!D8))),1,0) | E8: =IF(AND('CF_I'!E8<>"",IF(ISNUMBER('CF_I'!E8),OR('CF_I'!E8<>INT('CF_I'!E8),LEN(TEXT(ABS('CF_I'!E8),"0"))>12),TRUE)),1,0) | F8: =IF(AND('CF_I'!F8<>"",OR(LEN('CF_I'!F8)>3,COUNTIF(CL_MONEDA_ISO,'CF_I'!F8)=0)),1,0) | G8: =IF(AND('CF_I'!G8<>"",LEN('CF_I'!G8)>6),1,0) | H8: =IF(AND('CF_I'!H8<>"",LEN('CF_I'!H8)>34),1,0) | I8: =IF(AND('CF_I'!I8<>"",COUNTIF(CL_TIPO_RELACION_ACREDITADO,'CF_I'!I8)=0),1,0)
A9: =IF(AND('CF_I'!A9<>"",COUNTIF(CL_TIPO_OPERACION_CF_I,'CF_I'!A9)=0),1,0) | B9: =IF(AND('CF_I'!B9<>"",COUNTIF(CL_TIPO_FONDEO_CF_I,'CF_I'!B9)=0),1,0) | C9: =IF(AND('CF_I'!C9<>"",NOT(ISNUMBER('CF_I'!C9))),1,0) | D9: =IF(AND('CF_I'!D9<>"",NOT(ISNUMBER('CF_I'!D9))),1,0) | E9: =IF(AND('CF_I'!E9<>"",IF(ISNUMBER('CF_I'!E9),OR('CF_I'!E9<>INT('CF_I'!E9),LEN(TEXT(ABS('CF_I'!E9),"0"))>12),TRUE)),1,0) | F9: =IF(AND('CF_I'!F9<>"",OR(LEN('CF_I'!F9)>3,COUNTIF(CL_MONEDA_ISO,'CF_I'!F9)=0)),1,0) | G9: =IF(AND('CF_I'!G9<>"",LEN('CF_I'!G9)>6),1,0) | H9: =IF(AND('CF_I'!H9<>"",LEN('CF_I'!H9)>34),1,0) | I9: =IF(AND('CF_I'!I9<>"",COUNTIF(CL_TIPO_RELACION_ACREDITADO,'CF_I'!I9)=0),1,0)
A10: =IF(AND('CF_I'!A10<>"",COUNTIF(CL_TIPO_OPERACION_CF_I,'CF_I'!A10)=0),1,0) | B10: =IF(AND('CF_I'!B10<>"",COUNTIF(CL_TIPO_FONDEO_CF_I,'CF_I'!B10)=0),1,0) | C10: =IF(AND('CF_I'!C10<>"",NOT(ISNUMBER('CF_I'!C10))),1,0) | D10: =IF(AND('CF_I'!D10<>"",NOT(ISNUMBER('CF_I'!D10))),1,0) | E10: =IF(AND('CF_I'!E10<>"",IF(ISNUMBER('CF_I'!E10),OR('CF_I'!E10<>INT('CF_I'!E10),LEN(TEXT(ABS('CF_I'!E10),"0"))>12),TRUE)),1,0) | F10: =IF(AND('CF_I'!F10<>"",OR(LEN('CF_I'!F10)>3,COUNTIF(CL_MONEDA_ISO,'CF_I'!F10)=0)),1,0) | G10: =IF(AND('CF_I'!G10<>"",LEN('CF_I'!G10)>6),1,0) | H10: =IF(AND('CF_I'!H10<>"",LEN('CF_I'!H10)>34),1,0) | I10: =IF(AND('CF_I'!I10<>"",COUNTIF(CL_TIPO_RELACION_ACREDITADO,'CF_I'!I10)=0),1,0)
A11: =IF(AND('CF_I'!A11<>"",COUNTIF(CL_TIPO_OPERACION_CF_I,'CF_I'!A11)=0),1,0) | B11: =IF(AND('CF_I'!B11<>"",COUNTIF(CL_TIPO_FONDEO_CF_I,'CF_I'!B11)=0),1,0) | C11: =IF(AND('CF_I'!C11<>"",NOT(ISNUMBER('CF_I'!C11))),1,0) | D11: =IF(AND('CF_I'!D11<>"",NOT(ISNUMBER('CF_I'!D11))),1,0) | E11: =IF(AND('CF_I'!E11<>"",IF(ISNUMBER('CF_I'!E11),OR('CF_I'!E11<>INT('CF_I'!E11),LEN(TEXT(ABS('CF_I'!E11),"0"))>12),TRUE)),1,0) | F11: =IF(AND('CF_I'!F11<>"",OR(LEN('CF_I'!F11)>3,COUNTIF(CL_MONEDA_ISO,'CF_I'!F11)=0)),1,0) | G11: =IF(AND('CF_I'!G11<>"",LEN('CF_I'!G11)>6),1,0) | H11: =IF(AND('CF_I'!H11<>"",LEN('CF_I'!H11)>34),1,0) | I11: =IF(AND('CF_I'!I11<>"",COUNTIF(CL_TIPO_RELACION_ACREDITADO,'CF_I'!I11)=0),1,0)
A12: =IF(AND('CF_I'!A12<>"",COUNTIF(CL_TIPO_OPERACION_CF_I,'CF_I'!A12)=0),1,0) | B12: =IF(AND('CF_I'!B12<>"",COUNTIF(CL_TIPO_FONDEO_CF_I,'CF_I'!B12)=0),1,0) | C12: =IF(AND('CF_I'!C12<>"",NOT(ISNUMBER('CF_I'!C12))),1,0) | D12: =IF(AND('CF_I'!D12<>"",NOT(ISNUMBER('CF_I'!D12))),1,0) | E12: =IF(AND('CF_I'!E12<>"",IF(ISNUMBER('CF_I'!E12),OR('CF_I'!E12<>INT('CF_I'!E12),LEN(TEXT(ABS('CF_I'!E12),"0"))>12),TRUE)),1,0) | F12: =IF(AND('CF_I'!F12<>"",OR(LEN('CF_I'!F12)>3,COUNTIF(CL_MONEDA_ISO,'CF_I'!F12)=0)),1,0) | G12: =IF(AND('CF_I'!G12<>"",LEN('CF_I'!G12)>6),1,0) | H12: =IF(AND('CF_I'!H12<>"",LEN('CF_I'!H12)>34),1,0) | I12: =IF(AND('CF_I'!I12<>"",COUNTIF(CL_TIPO_RELACION_ACREDITADO,'CF_I'!I12)=0),1,0)
A13: =IF(AND('CF_I'!A13<>"",COUNTIF(CL_TIPO_OPERACION_CF_I,'CF_I'!A13)=0),1,0) | B13: =IF(AND('CF_I'!B13<>"",COUNTIF(CL_TIPO_FONDEO_CF_I,'CF_I'!B13)=0),1,0) | C13: =IF(AND('CF_I'!C13<>"",NOT(ISNUMBER('CF_I'!C13))),1,0) | D13: =IF(AND('CF_I'!D13<>"",NOT(ISNUMBER('CF_I'!D13))),1,0) | E13: =IF(AND('CF_I'!E13<>"",IF(ISNUMBER('CF_I'!E13),OR('CF_I'!E13<>INT('CF_I'!E13),LEN(TEXT(ABS('CF_I'!E13),"0"))>12),TRUE)),1,0) | F13: =IF(AND('CF_I'!F13<>"",OR(LEN('CF_I'!F13)>3,COUNTIF(CL_MONEDA_ISO,'CF_I'!F13)=0)),1,0) | G13: =IF(AND('CF_I'!G13<>"",LEN('CF_I'!G13)>6),1,0) | H13: =IF(AND('CF_I'!H13<>"",LEN('CF_I'!H13)>34),1,0) | I13: =IF(AND('CF_I'!I13<>"",COUNTIF(CL_TIPO_RELACION_ACREDITADO,'CF_I'!I13)=0),1,0)
... A201: =IF(AND('CF_I'!A201<>"",COUNTIF(CL_TIPO_OPERACION_CF_I,'CF_I'!A201)=0),1,0) | B201: =IF(AND('CF_I'!B201<>"",COUNTIF(CL_TIPO_FONDEO_CF_I,'CF_I'!B201)=0),1,0) | C201: =IF(AND('CF_I'!C201<>"",NOT(ISNUMBER('CF_I'!C201))),1,0) | D201: =IF(AND('CF_I'!D201<>"",NOT(ISNUMBER('CF_I'!D201))),1,0) | E201: =IF(AND('CF_I'!E201<>"",IF(ISNUMBER('CF_I'!E201),OR('CF_I'!E201<>INT('CF_I'!E201),LEN(TEXT(ABS('CF_I'!E201),"0"))>12),TRUE)),1,0) | F201: =IF(AND('CF_I'!F201<>"",OR(LEN('CF_I'!F201)>3,COUNTIF(CL_MONEDA_ISO,'CF_I'!F201)=0)),1,0) | G201: =IF(AND('CF_I'!G201<>"",LEN('CF_I'!G201)>6),1,0) | H201: =IF(AND('CF_I'!H201<>"",LEN('CF_I'!H201)>34),1,0) | I201: =IF(AND('CF_I'!I201<>"",COUNTIF(CL_TIPO_RELACION_ACREDITADO,'CF_I'!I201)=0),1,0)
